Backtracking/AllPermutationsOfString.py
Backtracking/KthPermutationSequence.py
Backtracking/MColouringProblem.py
Backtracking/NQueens.py
Backtracking/SudokuSolving.py
Backtracking/__init__.py
Dynamic Programming/CoinChange.py
Dynamic Programming/EggDropping.py
Dynamic Programming/KadanesAlgorithm.py
Dynamic Programming/LongestCommonSequence.py
Dynamic Programming/LongestCommonSubsequence.py
Dynamic Programming/LongestIncreasingSubsequence.py
Dynamic Programming/MaxProductSubarray.py
Dynamic Programming/PalindromePartitioning.py
Dynamic Programming/SubsetSum.py
Dynamic Programming/WordBreak.py
Dynamic Programming/ZeroOneKnapsack.py
Dynamic Programming/__init__.py
Graph/Kruskals.py
Graph/Prims.py
Graph/__init__.py
Greedy/FractionalKnapsack.py
Greedy/__init__.py
Stack/CheckForBalancedParentheses.py
Stack/LargestRectangleInHistogram.py
Stack/NextGreaterElement.py
Stack/__init__.py
String/KMPAlgorithm.py
String/LongestCommonPrefix.py
String/NextPermutation.py
String/PrefixFunction.py
String/RabinKarp.py
String/ReverseWordsInGivenString.py
String/__init__.py
Tree/BinaryTreeFromInorderAndPostorder.py
Tree/BinaryTreeFromInorderAndPreorder.py
Tree/BottomViewOfBinaryTree.py
Tree/HeightOfBinaryTree.py
Tree/InorderTraversalOfBinaryTree.py
Tree/LCAOfBinaryTree.py
Tree/LeftViewOfBinaryTree.py
Tree/MaximumPathSumInBinaryTree.py
Tree/PostorderTraversalOfBinaryTree.py
Tree/PreorderTraversalOfBinaryTree.py
Tree/RightViewOfBinaryTree.py
Tree/TopViewOfBinaryTree.py
Tree/__init__.py
ccalgo-0.0.1.dist-info/LICENSE
ccalgo-0.0.1.dist-info/METADATA
ccalgo-0.0.1.dist-info/WHEEL
ccalgo-0.0.1.dist-info/top_level.txt
ccalgo-0.0.1.dist-info/RECORD
