Metadata-Version: 2.1
Name: ccalgo
Version: 0.0.1
Summary: Using basic algorithms
Home-page: UNKNOWN
Author: Siddharth Marvania, Jenil Mehta
Author-email: 17bit046@nirmauni.ac.in, 17bit048@nirmauni.ac.in
License: UNKNOWN
Platform: UNKNOWN
Classifier: Programming Language :: Python :: 3
Classifier: License :: OSI Approved :: MIT License
Classifier: Operating System :: OS Independent
Requires-Python: >=3.6
